LICENCE
README.md
setup.py
py_lol/__init__.py
py_lol/account.py
py_lol/champion_mastery.py
py_lol/league.py
py_lol/match.py
py_lol/riot_api.py
py_lol/riot_services.py
py_lol/spectator.py
py_lol/summoner.py
py_lol/enum/__init__.py
py_lol/enum/region.py
py_lol/enum/serveur.py
py_lol_fr.egg-info/PKG-INFO
py_lol_fr.egg-info/SOURCES.txt
py_lol_fr.egg-info/dependency_links.txt
py_lol_fr.egg-info/requires.txt
py_lol_fr.egg-info/top_level.txt
tests/test.py