Metadata-Version: 2.1
Name: py_lol_fr
Version: 0.2
Summary: Un package qui permet l'utilisation simplifié de l'api de League of Legends
Home-page: https://github.com/Manoleau/py_lol
Author: Manolo
Author-email: emmanuelar.pro@gmail.com
Classifier: Programming Language :: Python :: 3.12
Classifier: License :: OSI Approved :: MIT License
Classifier: Operating System :: OS Independent
Requires-Python: >=3.12
License-File: LICENCE
Requires-Dist: requests
